{
  "$schema": ""
  "$id": ""
  "title": ""
  "description": ""
  "type": "object",
  "properties": {
	"wire-interface-2-0:wire-interface-configuration": {
		"type": "object",
		"properties": {
			"interface-name": 				{ "type": "string" },
			"interface-is-on": 				{ "type": "boolean" },
			"remote-wire-interface-name": 	{ "type": "string" }, 
		    "transceiver-is-on-list": {
				"type": "array",
				"items": {
					"type": "boolean"
				}
			}, 	   
			"auto-pmd-negotiation-is-on": 	{ "type": "boolean" },
			"fixed-pmd-kind": 				{ "type": "string" },
			"auto-negotiation-pmd-list": {
				"type": "array"
				"items": {
					"type": "string"
				}
			},			
			"auto-signal-ordering-is-on": 		{ "type": "boolean" },
			"fixed-signal-ordering-kind": { "enum": [
												"wire-interface-2-0:SIGNAL_ORDERING_KIND_TYPE_MDI",
												"wire-interface-2-0:SIGNAL_ORDERING_KIND_TYPE_MDI_X",
												"wire-interface-2-0:SIGNAL_ORDERING_KIND_TYPE_NOT_YET_DEFINED"
											]
			},
			"wavelength-list": {
				"type": "array",
				"items": {
					"type": "number"
				}
			},
			"rx-sync-preference": 			{ "type": "string" }, 
			"short-reach-mode-is-on": 		{ "type": "boolean" },		
			"eee-is-on": 					{ "type": "boolean" }, 
			"unidirectional-operation-is-on": { "type": "boolean" }, 
			"number-of-bip-errors-per-ses":	{ "type": "number" },
			"restart-pmd-negotiation-is-on":{ "type": "boolean" }, 
			"isolation-is-on": 				{ "type": "boolean" },
			"loop-back-kind-on": { "enum": [
										"wire-interface-2-0:LOOP_BACK_TYPE_NONE",
										"wire-interface-2-0:LOOP_BACK_TYPE_BACK_TO_EXTERNAL",
										"wire-interface-2-0:LOOP_BACK_TYPE_BACK_TO_INTERNAL",
										"wire-interface-2-0:LOOP_BACK_TYPE_NOT_YET_DEFINED"
									]
			}
			"maintenance-timer": 			{ "type": "number" },
			"problem-kind-severity-list": {
				"type": "array",
				"items": {
					"problem-kind-name": 	{ "type": "string" },
					"problem-kind-severity": { "enum": [
												   "wire-interface-2-0:SEVERITY_TYPE_NON_ALARMED",
												   "wire-interface-2-0:SEVERITY_TYPE_WARNING",
												   "wire-interface-2-0:SEVERITY_TYPE_MINOR",
												   "wire-interface-2-0:SEVERITY_TYPE_MAJOR",
												   "wire-interface-2-0:SEVERITY_TYPE_CRITICAL",
												   "wire-interface-2-0:SEVERITY_TYPE_NOT_YET_DEFINED"
												]
					}
				}
			}, 
			"performance-monitoring-is-on": { "type": "boolean" } 
}
		}
	}	
 }